ape_openzeppelin/__init__.py
ape_openzeppelin/dependency.py
ape_openzeppelin/py.typed
ape_openzeppelin/utils.py
ape_openzeppelin/version.py
ape_openzeppelin-0.8.0.dist-info/LICENSE
ape_openzeppelin-0.8.0.dist-info/METADATA
ape_openzeppelin-0.8.0.dist-info/WHEEL
ape_openzeppelin-0.8.0.dist-info/top_level.txt
ape_openzeppelin-0.8.0.dist-info/RECORD
